_examples/__init__.py
_examples/sensitivity_analysis.py
examples/__init__.py
sensitivity/__init__.py
sensitivity/_ignore_warn.py
sensitivity/colors.py
sensitivity/df.py
sensitivity/hexbin.py
sensitivity/main.py
tests/__init__.py
tests/base.py
tests/conftest.py
tests/test_df.py
tests/test_sensitivity_analyzer.py
sensitivity-0.2.8.dist-info/LICENSE.md
sensitivity-0.2.8.dist-info/METADATA
sensitivity-0.2.8.dist-info/WHEEL
sensitivity-0.2.8.dist-info/top_level.txt
sensitivity-0.2.8.dist-info/RECORD
