Metadata-Version: 2.1
Name: sensitivity
Version: 0.2.8
Summary: Python Sensitivity Analysis - Gradient DataFrames and Hex-Bin Plots
Home-page: https://github.com/nickderobertis/sensitivity
Author: Nick DeRobertis
Author-email: whoopnip@gmail.com
License: MIT
Project-URL: Code, https://github.com/nickderobertis/sensitivity
Project-URL: Documentation, https://nickderobertis.github.io/sensitivity
Classifier: Development Status :: 3 - Alpha
Classifier: Intended Audience :: Developers
Classifier: Programming Language :: Python :: 3.6
Classifier: Programming Language :: Python :: 3.7
License-File: LICENSE.md
Requires-Dist: pandas (>=1)
Requires-Dist: matplotlib
Requires-Dist: IPython
Requires-Dist: tqdm
